{"id":"helpinghand","n":"Move:HELPINGHAND","s":"PRAS- Strike.png","cs":192,"cr":5,"fps":20,"f":[{"d":1,"c":[{"i":7,"fc":3,"x":176,"y":180,"a":0.5490196078431373},{"i":8,"fc":3,"x":280,"y":180,"a":0.5490196078431373}]},{"d":1,"c":[{"i":7,"fc":3,"x":176,"y":180},{"i":8,"fc":3,"x":280,"y":180}]},{"d":1,"c":[{"i":7,"fc":3,"x":204,"y":180},{"i":8,"fc":3,"x":260,"y":180}]},{"d":1,"c":[{"i":7,"fc":3,"x":232,"y":180},{"i":8,"fc":3,"x":240,"y":180}]},{"d":1,"c":[{"i":7,"fc":3,"x":216,"y":180},{"i":8,"fc":3,"x":256,"y":180}]},{"d":1,"c":[{"i":7,"fc":3,"x":200,"y":180},{"i":8,"fc":3,"x":272,"y":180}]},{"d":1,"c":[{"i":7,"fc":3,"x":216,"y":180},{"i":8,"fc":3,"x":256,"y":180}]},{"d":1,"c":[{"i":7,"fc":3,"x":232,"y":180},{"i":8,"fc":3,"x":240,"y":180}]},{"d":1,"c":[{"i":7,"fc":3,"x":232,"y":180,"a":0.5490196078431373},{"i":8,"fc":3,"x":240,"y":180,"a":0.5490196078431373}]},{"d":1,"c":[]}],"t":[{"f":0,"tt":0,"n":"PRSFX- Helping Hand.wav","d":5,"v":100}]}