{"id":"magneticflux","n":"Move:MAGNETICFLUX","s":"PRAS- Electric.png","cs":192,"cr":5,"fps":20,"f":[{"d":1,"c":[]},{"d":1,"c":[]},{"d":1,"c":[]},{"d":1,"c":[]},{"d":1,"c":[]},{"d":1,"c":[]},{"d":1,"c":[]},{"d":1,"c":[]},{"d":1,"c":[]},{"d":1,"c":[]},{"d":1,"c":[]},{"d":1,"c":[]},{"d":1,"c":[]},{"d":1,"c":[]},{"d":1,"c":[]},{"d":1,"c":[]},{"d":1,"c":[]},{"d":1,"c":[]},{"d":1,"c":[]},{"d":1,"c":[]},{"d":1,"c":[]},{"d":1,"c":[]},{"d":1,"c":[]},{"d":1,"c":[]},{"d":1,"c":[]},{"d":1,"c":[]},{"d":1,"c":[]},{"d":1,"c":[]},{"d":1,"c":[]},{"d":1,"c":[{"i":0,"fc":4,"x":231,"y":156,"a":0.5490196078431373}]},{"d":1,"c":[{"i":0,"fc":4,"x":231,"y":156}]},{"d":1,"c":[{"i":1,"fc":4,"x":231,"y":156}]},{"d":1,"c":[{"i":2,"fc":4,"x":231,"y":156}]},{"d":1,"c":[{"i":3,"fc":4,"x":231,"y":156}]},{"d":1,"c":[{"i":3,"fc":4,"x":231,"y":156,"a":0.5490196078431373}]},{"d":1,"c":[]},{"d":1,"c":[]},{"d":1,"c":[]},{"d":1,"c":[]},{"d":1,"c":[{"i":0,"fc":4,"x":60,"y":179,"a":0.5490196078431373}]},{"d":1,"c":[{"i":0,"fc":4,"x":60,"y":179}]},{"d":1,"c":[{"i":1,"fc":4,"x":60,"y":179}]},{"d":1,"c":[{"i":2,"fc":4,"x":60,"y":179}]},{"d":1,"c":[{"i":3,"fc":4,"x":60,"y":179}]},{"d":1,"c":[{"i":3,"fc":4,"x":60,"y":179,"a":0.5490196078431373}]},{"d":1,"c":[]},{"d":1,"c":[]},{"d":1,"c":[]},{"d":1,"c":[]},{"d":1,"c":[{"i":0,"fc":4,"x":158,"y":235,"a":0.5490196078431373}]},{"d":1,"c":[{"i":0,"fc":4,"x":158,"y":235}]},{"d":1,"c":[{"i":1,"fc":4,"x":158,"y":235}]},{"d":1,"c":[{"i":2,"fc":4,"x":158,"y":235}]},{"d":1,"c":[{"i":3,"fc":4,"x":158,"y":235}]},{"d":1,"c":[{"i":3,"fc":4,"x":158,"y":235,"a":0.5686274509803921}]},{"d":1,"c":[]},{"d":1,"c":[]},{"d":1,"c":[]},{"d":1,"c":[]},{"d":1,"c":[]},{"d":1,"c":[]},{"d":1,"c":[]},{"d":1,"c":[]},{"d":1,"c":[]},{"d":1,"c":[]}],"t":[{"f":0,"tt":0,"n":"PRSFX- Magnetic Flux.wav","d":5,"v":100},{"f":0,"tt":1,"n":"PRAS- Electric Terrain BG.png","d":5},{"f":0,"tt":2,"d":5},{"f":59,"tt":2,"d":5}]}