{"id":"razorleaf","n":"Move:RAZORLEAF","s":"PRAS- Grass.png","cs":192,"cr":5,"fps":20,"f":[{"d":1,"c":[{"i":8,"fc":3,"x":87,"y":170,"a":0.5882352941176471},{"i":8,"fc":3,"x":206,"y":238,"a":0.5882352941176471},{"i":8,"fc":3,"x":83,"y":229,"a":0.5882352941176471},{"i":8,"fc":3,"x":155,"y":192,"a":0.5882352941176471},{"i":8,"fc":3,"x":139,"y":254,"a":0.5882352941176471}]},{"d":1,"c":[{"i":8,"fc":3,"x":87,"y":170},{"i":8,"fc":3,"x":206,"y":238},{"i":8,"fc":3,"x":83,"y":229},{"i":8,"fc":3,"x":155,"y":192},{"i":8,"fc":3,"x":139,"y":254}]},{"d":1,"c":[{"i":9,"fc":3,"x":87,"y":160},{"i":9,"fc":3,"x":206,"y":228},{"i":9,"fc":3,"x":83,"y":219},{"i":9,"fc":3,"x":155,"y":182},{"i":9,"fc":3,"x":139,"y":244},{"i":8,"fc":3,"x":197,"y":205,"a":0.5882352941176471},{"i":8,"fc":3,"x":115,"y":208,"a":0.5882352941176471},{"i":8,"fc":3,"x":112,"y":263,"a":0.5882352941176471},{"i":8,"fc":3,"x":127,"y":162,"a":0.5882352941176471}]},{"d":1,"c":[{"i":10,"fc":3,"x":87,"y":150},{"i":10,"fc":3,"x":206,"y":218},{"i":10,"fc":3,"x":83,"y":209},{"i":10,"fc":3,"x":155,"y":172},{"i":10,"fc":3,"x":139,"y":234},{"i":8,"fc":3,"x":197,"y":205},{"i":8,"fc":3,"x":115,"y":208},{"i":8,"fc":3,"x":112,"y":263},{"i":8,"fc":3,"x":127,"y":162}]},{"d":1,"c":[{"i":11,"fc":3,"x":87,"y":140},{"i":11,"fc":3,"x":206,"y":208},{"i":11,"fc":3,"x":83,"y":199},{"i":11,"fc":3,"x":155,"y":162},{"i":11,"fc":3,"x":139,"y":224},{"i":9,"fc":3,"x":197,"y":195},{"i":9,"fc":3,"x":115,"y":198},{"i":9,"fc":3,"x":112,"y":253},{"i":9,"fc":3,"x":127,"y":152}]},{"d":1,"c":[{"i":8,"fc":3,"x":87,"y":130,"a":0.5882352941176471},{"i":8,"fc":3,"x":206,"y":198,"a":0.5882352941176471},{"i":8,"fc":3,"x":83,"y":189,"a":0.5882352941176471},{"i":8,"fc":3,"x":155,"y":152,"a":0.5882352941176471},{"i":8,"fc":3,"x":139,"y":214,"a":0.5882352941176471},{"i":8,"fc":3,"x":197,"y":185,"a":0.792156862745098},{"i":8,"fc":3,"x":115,"y":188,"a":0.792156862745098},{"i":8,"fc":3,"x":112,"y":243,"a":0.792156862745098},{"i":8,"fc":3,"x":127,"y":142,"a":0.792156862745098}]},{"d":1,"c":[{"i":8,"fc":3,"x":87,"y":130},{"i":8,"fc":3,"x":206,"y":198},{"i":8,"fc":3,"x":83,"y":189},{"i":8,"fc":3,"x":155,"y":152},{"i":8,"fc":3,"x":139,"y":214},{"i":8,"fc":3,"x":197,"y":175,"a":0.6901960784313725},{"i":8,"fc":3,"x":115,"y":178,"a":0.6901960784313725},{"i":8,"fc":3,"x":112,"y":233,"a":0.6901960784313725},{"i":8,"fc":3,"x":127,"y":132,"a":0.6901960784313725}]},{"d":1,"c":[{"i":9,"fc":3,"x":87,"y":136},{"i":9,"fc":3,"x":206,"y":206},{"i":9,"fc":3,"x":81,"y":197},{"i":9,"fc":3,"x":155,"y":160},{"i":9,"fc":3,"x":139,"y":223},{"i":8,"fc":3,"x":197,"y":165,"a":0.5882352941176471},{"i":8,"fc":3,"x":115,"y":168,"a":0.5882352941176471},{"i":8,"fc":3,"x":112,"y":223,"a":0.5882352941176471},{"i":8,"fc":3,"x":127,"y":122,"a":0.5882352941176471}]},{"d":1,"c":[{"i":10,"fc":3,"x":87,"y":143},{"i":10,"fc":3,"x":206,"y":214},{"i":10,"fc":3,"x":79,"y":205},{"i":10,"fc":3,"x":156,"y":168},{"i":10,"fc":3,"x":140,"y":232},{"i":8,"fc":3,"x":197,"y":165},{"i":8,"fc":3,"x":115,"y":168},{"i":8,"fc":3,"x":112,"y":223},{"i":8,"fc":3,"x":127,"y":122}]},{"d":1,"c":[{"i":11,"fc":3,"x":87,"y":150},{"i":11,"fc":3,"x":207,"y":222},{"i":11,"fc":3,"x":77,"y":213},{"i":11,"fc":3,"x":157,"y":176},{"i":11,"fc":3,"x":141,"y":242},{"i":9,"fc":3,"x":192,"y":171},{"i":9,"fc":3,"x":107,"y":173},{"i":9,"fc":3,"x":116,"y":225},{"i":9,"fc":3,"x":133,"y":126}]},{"d":1,"c":[{"i":12,"fc":3,"x":87,"y":156},{"i":12,"fc":3,"x":207,"y":230},{"i":12,"fc":3,"x":75,"y":221},{"i":12,"fc":3,"x":158,"y":184},{"i":12,"fc":3,"x":142,"y":251},{"i":10,"fc":3,"x":187,"y":178},{"i":10,"fc":3,"x":100,"y":178},{"i":10,"fc":3,"x":120,"y":228},{"i":10,"fc":3,"x":140,"y":130}]},{"d":1,"c":[{"i":13,"fc":3,"x":87,"y":163},{"i":13,"fc":3,"x":207,"y":238},{"i":13,"fc":3,"x":73,"y":229},{"i":13,"fc":3,"x":159,"y":192},{"i":13,"fc":3,"x":143,"y":260},{"i":11,"fc":3,"x":182,"y":185},{"i":11,"fc":3,"x":93,"y":184},{"i":11,"fc":3,"x":124,"y":231},{"i":11,"fc":3,"x":147,"y":134}]},{"d":1,"c":[{"i":14,"fc":3,"x":88,"y":170},{"i":14,"fc":3,"x":208,"y":246},{"i":14,"fc":3,"x":72,"y":237},{"i":14,"fc":3,"x":160,"y":200},{"i":14,"fc":3,"x":144,"y":270},{"i":12,"fc":3,"x":177,"y":191},{"i":12,"fc":3,"x":86,"y":189},{"i":12,"fc":3,"x":128,"y":233},{"i":12,"fc":3,"x":154,"y":138}]},{"d":1,"c":[{"i":14,"fc":3,"x":88,"y":170},{"i":14,"fc":3,"x":144,"y":271},{"i":14,"fc":3,"x":72,"y":237},{"i":14,"fc":3,"x":160,"y":200,"a":0.5882352941176471},{"i":14,"fc":3,"x":208,"y":246},{"i":13,"fc":3,"x":172,"y":198},{"i":13,"fc":3,"x":79,"y":194},{"i":13,"fc":3,"x":132,"y":236},{"i":13,"fc":3,"x":161,"y":142}]},{"d":1,"c":[{"i":15,"fc":3,"x":92,"y":174},{"i":15,"fc":3,"x":146,"y":274},{"i":15,"fc":3,"x":76,"y":240},{"i":15,"fc":3,"x":162,"y":203},{"i":15,"fc":3,"x":212,"y":250},{"i":15,"fc":3,"x":168,"y":205},{"i":14,"fc":3,"x":72,"y":200},{"i":14,"fc":3,"x":136,"y":239},{"i":14,"fc":3,"x":168,"y":146}]},{"d":1,"c":[{"i":8,"fc":3,"x":96,"y":177,"a":0.5882352941176471},{"i":8,"fc":3,"x":150,"y":277,"a":0.5882352941176471},{"i":8,"fc":3,"x":78,"y":243,"a":0.5882352941176471},{"i":8,"fc":3,"x":164,"y":206,"a":0.5882352941176471},{"i":8,"fc":3,"x":217,"y":252,"a":0.5882352941176471},{"i":15,"fc":3,"x":168,"y":205,"a":0.5882352941176471},{"i":14,"fc":3,"x":72,"y":200,"a":0.5882352941176471},{"i":14,"fc":3,"x":136,"y":239,"a":0.5882352941176471},{"i":14,"fc":3,"x":168,"y":146,"a":0.5882352941176471}]},{"d":1,"c":[{"i":15,"fc":3,"x":76,"y":204},{"i":14,"fc":3,"x":140,"y":243},{"i":14,"fc":3,"x":172,"y":150}]},{"d":1,"c":[{"i":16,"fc":3,"x":80,"y":208},{"i":15,"fc":3,"x":142,"y":247},{"i":15,"fc":3,"x":176,"y":154}]},{"d":1,"c":[{"i":4,"fc":3,"x":168,"y":227,"a":0.5882352941176471}]},{"d":1,"c":[{"i":4,"fc":3,"x":168,"y":227}]},{"d":1,"c":[{"i":5,"fc":3,"x":232,"y":191},{"i":4,"fc":3,"x":126,"y":209,"a":0.5882352941176471},{"i":8,"fc":3,"x":165,"y":191,"a":0.5882352941176471},{"i":8,"fc":3,"x":189,"y":237,"a":0.5882352941176471}]},{"d":1,"c":[{"i":6,"fc":3,"x":296,"y":156},{"i":4,"fc":3,"x":126,"y":209},{"i":9,"fc":3,"x":193,"y":175},{"i":9,"fc":3,"x":229,"y":222}]},{"d":1,"c":[{"i":7,"fc":3,"x":360,"y":121},{"i":5,"fc":3,"x":197,"y":176},{"i":4,"fc":3,"x":154,"y":233,"a":0.5882352941176471},{"i":10,"fc":3,"x":222,"y":159},{"i":10,"fc":3,"x":270,"y":207}]},{"d":1,"c":[{"i":4,"fc":3,"x":424,"y":86},{"i":6,"fc":3,"x":268,"y":144},{"i":4,"fc":3,"x":154,"y":233},{"i":11,"fc":3,"x":250,"y":143},{"i":11,"fc":3,"x":311,"y":193},{"i":16,"fc":3,"x":238,"y":236,"a":0.5882352941176471},{"i":16,"fc":3,"x":180,"y":196,"a":0.5882352941176471}]},{"d":1,"c":[{"i":5,"fc":3,"x":488,"y":51},{"i":7,"fc":3,"x":339,"y":112},{"i":5,"fc":3,"x":220,"y":196},{"i":12,"fc":3,"x":302,"y":129},{"i":12,"fc":3,"x":352,"y":178},{"i":16,"fc":3,"x":284,"y":208},{"i":16,"fc":3,"x":217,"y":177}]},{"d":1,"c":[{"i":6,"fc":3,"x":552,"y":16,"a":0.5686274509803921},{"i":4,"fc":3,"x":410,"y":79},{"i":6,"fc":3,"x":286,"y":160},{"i":13,"fc":3,"x":308,"y":112,"a":0.5882352941176471},{"i":13,"fc":3,"x":393,"y":164,"a":0.5882352941176471},{"i":16,"fc":3,"x":330,"y":181},{"i":16,"fc":3,"x":254,"y":159}]},{"d":1,"c":[{"i":5,"fc":3,"x":481,"y":47},{"i":7,"fc":3,"x":353,"y":124},{"i":16,"fc":3,"x":376,"y":153},{"i":16,"fc":3,"x":291,"y":140}]},{"d":1,"c":[{"i":6,"fc":3,"x":552,"y":15,"a":0.5686274509803921},{"i":4,"fc":3,"x":419,"y":87},{"i":16,"fc":3,"x":422,"y":126},{"i":16,"fc":3,"x":328,"y":122}]},{"d":1,"c":[{"i":5,"fc":3,"x":485,"y":51}]},{"d":1,"c":[{"i":6,"fc":3,"x":552,"y":15,"a":0.5686274509803921}]}],"t":[{"f":17,"tt":0,"n":"PRSFX- Razor Leaf1.wav","v":100},{"f":0,"tt":0,"n":"PRSFX- Razor Leaf2.wav","d":5,"v":100}]}